hashgrid/__init__.py
hashgrid-0.1.1.dist-info/METADATA
hashgrid-0.1.1.dist-info/WHEEL
hashgrid-0.1.1.dist-info/licenses/LICENSE
hashgrid-0.1.1.dist-info/RECORD
