Metadata-Version: 2.4
Name: hashgrid
Version: 0.1.1
Summary: Distributed neural question answering framework
Author-email: Lucian Bicsi <lucian@hashgrid.ai>
License: MIT
License-File: LICENSE
Keywords: grid,hash,hashgrid
Classifier: Development Status :: 3 - Alpha
Classifier: Intended Audience :: Developers
Classifier: License :: OSI Approved :: MIT License
Classifier: Programming Language :: Python :: 3
Classifier: Programming Language :: Python :: 3.13
Requires-Python: >=3.13
Requires-Dist: build>=1.3.0
Requires-Dist: twine>=6.2.0
